pppc/__init__.py
pppc/compiler.py
pppc/core.py
pppc/decorators.py
pppc/exceptions.py
pppc/templates.py
pppc/version.py
pppc/utils/__init__.py
pppc/utils/file_manager.py
pppc/utils/jar_builder.py
pppc/utils/java_compiler.py
pppc/utils/java_generator.py
pppc/utils/plugin_yml.py
pppc/utils/template_manager.py
pppc/utils/validation.py
pppc-0.1.8.dist-info/LICENSE
pppc-0.1.8.dist-info/METADATA
pppc-0.1.8.dist-info/WHEEL
pppc-0.1.8.dist-info/top_level.txt
pppc-0.1.8.dist-info/RECORD
