Metadata-Version: 2.1
Name: pppc
Version: 0.1.8
Summary: Create Minecraft Paper plugins using Python
Home-page: https://github.com/retrotee/pppc
Author: retrotee
Project-URL: Bug Tracker, https://github.com/retrotee/pppc/issues
Project-URL: Documentation, https://github.com/retrotee/pppc#readme
Classifier: Development Status :: 3 - Alpha
Classifier: Intended Audience :: Developers
Classifier: Topic :: Games/Entertainment
Classifier: Programming Language :: Python :: 3
Classifier: Programming Language :: Python :: 3.8
Classifier: Programming Language :: Python :: 3.9
Classifier: Programming Language :: Python :: 3.10
Classifier: Programming Language :: Python :: 3.11
Classifier: License :: OSI Approved :: MIT License
Classifier: Operating System :: OS Independent
Requires-Python: >=3.8
License-File: LICENSE
Requires-Dist: jinja2>=3.0.0
Requires-Dist: PyYAML>=6.0
Requires-Dist: typing-extensions>=4.0.0
Requires-Dist: dataclasses>=0.6; python_version < "3.7"
Requires-Dist: packaging>=21.0
Provides-Extra: dev
Requires-Dist: pytest>=7.0.0; extra == "dev"
Requires-Dist: pytest-cov>=3.0.0; extra == "dev"
Requires-Dist: mypy>=0.950; extra == "dev"
Requires-Dist: flake8>=4.0.0; extra == "dev"
Requires-Dist: tox>=3.24.0; extra == "dev"
Requires-Dist: build>=0.10.0; extra == "dev"
Requires-Dist: twine>=4.0.0; extra == "dev"
